rtlviz/__init__.py
rtlviz/__main__.py
rtlviz/cli.py
rtlviz/diagram_validator.py
rtlviz/dot_generator.py
rtlviz/llm_analyzer.py
rtlviz/rtl_parser.py
rtlviz/server.py
rtlviz/setup.py
rtlviz/telemetry.py
rtlviz/assets/PROMPT.md
rtlviz/assets/SKILL.md
rtlviz-0.4.9.dist-info/METADATA
rtlviz-0.4.9.dist-info/WHEEL
rtlviz-0.4.9.dist-info/entry_points.txt
rtlviz-0.4.9.dist-info/RECORD
