Metadata-Version: 2.4
Name: rtlviz
Version: 0.4.9
Summary: MCP Server for AI-powered RTL diagram generation from Verilog source
Project-URL: Homepage, https://github.com/rtlviz/rtlviz
Project-URL: Repository, https://github.com/rtlviz/rtlviz
Author-email: Naveen Venkat <naveenvenkat1711@gmail.com>, Hari Ayyappane <hari.ayyaps@gamil.com>
License-Expression: MIT
Keywords: ai,block-diagram,diagram,graphviz,hdl,mcp,rtl,verilog
Classifier: Development Status :: 3 - Alpha
Classifier: Intended Audience :: Developers
Classifier: License :: OSI Approved :: MIT License
Classifier: Programming Language :: Python :: 3
Classifier: Programming Language :: Python :: 3.10
Classifier: Programming Language :: Python :: 3.11
Classifier: Programming Language :: Python :: 3.12
Requires-Python: >=3.10
Requires-Dist: graphviz>=0.20
Requires-Dist: mcp>=1.0.0
